pyprodir
