Metadata-Version: 2.1
Name: pyprodir
Version: 2.0.0
Summary: prepend directory of importer's pyproject.toml to sys.path
Home-page: https://github.com/pypa/sampleproject
Author: churunmin
Author-email: churunmin@outlook.com
License: MIT
Platform: UNKNOWN
Requires-Python: >=3.6
